{
  "loss_kwargs": {
    "class_name": "training.loss.EPD_loss"
  },
  "pred_kwargs": {
    "class_name": "training.networks.EPD_predictor",
    "num_steps": 11,
    "sampler_stu": "epd",
    "sampler_tea": "dpm",
    "M": 1,
    "guidance_type": "cfg",
    "guidance_rate": 7.5,
    "schedule_rho": 1.0,
    "schedule_type": "discrete",
    "afs": false,
    "dataset_name": "ms_coco",
    "scale_dir": 0.0,
    "scale_time": 0.0,
    "num_points": 2,
    "fcn": false,
    "alpha": 10.0,
    "max_order": 2,
    "predict_x0": false,
    "lower_order_final": true,
    "backend": "ldm",
    "backend_config": {
      "resolution": 1024
    },
    "img_resolution": 1024
  },
  "optimizer_kwargs": {
    "class_name": "torch.optim.Adam",
    "lr": 0.01,
    "betas": [
      0.9,
      0.999
    ],
    "eps": 1e-08
  },
  "cos_lr_schedule": false,
  "alpha": 10.0,
  "total_kimg": 5,
  "kimg_per_tick": 1,
  "snapshot_ticks": 5,
  "state_dump_ticks": 5,
  "dataset_name": "ms_coco",
  "batch_size": 32,
  "batch_gpu": null,
  "gpus": 8,
  "cudnn_benchmark": true,
  "guidance_type": "cfg",
  "guidance_rate": 7.5,
  "prompt_path": null,
  "seed": 0,
  "run_dir": "./exps/fake-sd15-11",
  "export_info": {
    "source_run": "/work/nvme/betk/zli42/RLEPD/exps/20251214-134452-sd15_k5",
    "policy_checkpoint": "/work/nvme/betk/zli42/RLEPD/exps/20251214-134452-sd15_k5/checkpoints/policy-step004000.pt",
    "sanitized_rows": {
      "reordered_rows": 0,
      "adjusted_rows": 0
    }
  }
}